{
    "feeder": {
        "IEEE-34B": {
            "vrms": 24900.0
        }
    },
    "bus": {
        "800": {
            "x": 0.0,
            "y": 0.0
        },
        "802": {
            "x": 0.7864,
            "y": 0.0
        },
        "806": {
            "x": 1.3137,
            "y": 0.0
        },
        "808": {
            "x": 11.1374,
            "y": 0.0
        },
        "810": {
            "x": 11.1374,
            "y": -1.7691
        },
        "812": {
            "x": 22.5674,
            "y": 0.0
        },
        "814": {
            "x": 31.6291,
            "y": 0.0
        },
        "816": {
            "x": 31.7236,
            "y": 0.0
        },
        "818": {
            "x": 31.7236,
            "y": 0.5212
        },
        "820": {
            "x": 31.7236,
            "y": 15.1973
        },
        "822": {
            "x": 31.7236,
            "y": 19.3853
        },
        "824": {
            "x": 34.8356,
            "y": 0.0
        },
        "826": {
            "x": 35.7591,
            "y": 0.0
        },
        "828": {
            "x": 34.8356,
            "y": -0.256
        },
        "830": {
            "x": 41.0657,
            "y": -0.256
        },
        "854": {
            "x": 41.2242,
            "y": -0.256
        },
        "856": {
            "x": 48.3352,
            "y": -0.256
        },
        "852": {
            "x": 41.2242,
            "y": 10.9698
        },
        "858": {
            "x": 41.2242,
            "y": 12.4633
        },
        "864": {
            "x": 41.2242,
            "y": 12.957
        },
        "834": {
            "x": 43.0012,
            "y": 12.4633
        },
        "842": {
            "x": 43.0012,
            "y": 12.5486
        },
        "844": {
            "x": 43.0012,
            "y": 12.9601
        },
        "846": {
            "x": 43.0012,
            "y": 14.0696
        },
        "848": {
            "x": 43.0012,
            "y": 14.2311
        },
        "860": {
            "x": 43.6169,
            "y": 12.4633
        },
        "836": {
            "x": 44.4337,
            "y": 12.4633
        },
        "840": {
            "x": 44.6959,
            "y": 12.4633
        },
        "862": {
            "x": 44.4337,
            "y": 12.3779
        },
        "838": {
            "x": 44.4337,
            "y": 10.8966
        }
    },
    "branch": {
        "L1": {
            "from": "800",
            "to": "802",
            "length": 786.384,
            "phase": "ABCN",
            "cable": "1/0",
            "pole": "IEEE_500"
        },
        "L2": {
            "from": "802",
            "to": "806",
            "length": 527.304,
            "phase": "ABCN",
            "cable": "1/0",
            "pole": "IEEE_500"
        },
        "L3": {
            "from": "806",
            "to": "808",
            "length": 9823.704,
            "phase": "ABCN",
            "cable": "1/0",
            "pole": "IEEE_500"
        },
        "L4": {
            "from": "808",
            "to": "810",
            "length": 1769.0592000000001,
            "phase": "BN",
            "cable": "#4  6/1",
            "pole": "IEEE_510"
        },
        "L5": {
            "from": "808",
            "to": "812",
            "length": 11430.0,
            "phase": "ABCN",
            "cable": "1/0",
            "pole": "IEEE_500"
        },
        "L6": {
            "from": "812",
            "to": "814",
            "length": 9061.704000000002,
            "phase": "ABCN",
            "cable": "1/0",
            "pole": "IEEE_500"
        },
        "L7": {
            "from": "816",
            "to": "818",
            "length": 521.208,
            "phase": "AN",
            "cable": "#4  6/1",
            "pole": "IEEE_510"
        },
        "L8": {
            "from": "816",
            "to": "824",
            "length": 3112.008,
            "phase": "ABCN",
            "cable": "#2  6/1",
            "pole": "IEEE_500"
        },
        "L9": {
            "from": "818",
            "to": "820",
            "length": 14676.12,
            "phase": "AN",
            "cable": "#4  6/1",
            "pole": "IEEE_510"
        },
        "L10": {
            "from": "820",
            "to": "822",
            "length": 4187.952,
            "phase": "AN",
            "cable": "#4  6/1",
            "pole": "IEEE_510"
        },
        "L11": {
            "from": "824",
            "to": "826",
            "length": 923.544,
            "phase": "BN",
            "cable": "#4  6/1",
            "pole": "IEEE_510"
        },
        "L12": {
            "from": "824",
            "to": "828",
            "length": 256.032,
            "phase": "ABCN",
            "cable": "#2  6/1",
            "pole": "IEEE_500"
        },
        "L13": {
            "from": "828",
            "to": "830",
            "length": 6230.112,
            "phase": "ABCN",
            "cable": "#2  6/1",
            "pole": "IEEE_500"
        },
        "L14": {
            "from": "830",
            "to": "854",
            "length": 158.496,
            "phase": "ABCN",
            "cable": "#2  6/1",
            "pole": "IEEE_500"
        },
        "L15": {
            "from": "852",
            "to": "858",
            "length": 1493.52,
            "phase": "ABCN",
            "cable": "#2  6/1",
            "pole": "IEEE_500"
        },
        "L16": {
            "from": "860",
            "to": "834",
            "length": 615.696,
            "phase": "ABCN",
            "cable": "#2  6/1",
            "pole": "IEEE_500"
        },
        "L17": {
            "from": "834",
            "to": "842",
            "length": 85.34400000000001,
            "phase": "ABCN",
            "cable": "#2  6/1",
            "pole": "IEEE_500"
        },
        "L18": {
            "from": "836",
            "to": "840",
            "length": 262.12800000000004,
            "phase": "ABCN",
            "cable": "#2  6/1",
            "pole": "IEEE_500"
        },
        "L19": {
            "from": "836",
            "to": "862",
            "length": 85.34400000000001,
            "phase": "ABCN",
            "cable": "#2  6/1",
            "pole": "IEEE_500"
        },
        "L20": {
            "from": "842",
            "to": "844",
            "length": 411.48,
            "phase": "ABCN",
            "cable": "#2  6/1",
            "pole": "IEEE_500"
        },
        "L21": {
            "from": "844",
            "to": "846",
            "length": 1109.472,
            "phase": "ABCN",
            "cable": "#2  6/1",
            "pole": "IEEE_500"
        },
        "L22": {
            "from": "846",
            "to": "848",
            "length": 161.54399999999998,
            "phase": "ABCN",
            "cable": "#2  6/1",
            "pole": "IEEE_500"
        },
        "L23": {
            "from": "814",
            "to": "816",
            "length": 94.488,
            "phase": "ABCN",
            "cable": "#2  6/1",
            "pole": "IEEE_500"
        },
        "L24": {
            "from": "854",
            "to": "856",
            "length": 7110.984,
            "phase": "BN",
            "cable": "#4  6/1",
            "pole": "IEEE_510"
        },
        "L25": {
            "from": "854",
            "to": "852",
            "length": 11225.784000000001,
            "phase": "ABCN",
            "cable": "#2  6/1",
            "pole": "IEEE_500"
        },
        "L26": {
            "from": "858",
            "to": "864",
            "length": 493.776,
            "phase": "AN",
            "cable": "#4  6/1",
            "pole": "IEEE_510"
        },
        "L27": {
            "from": "858",
            "to": "834",
            "length": 1776.984,
            "phase": "ABCN",
            "cable": "#2  6/1",
            "pole": "IEEE_500"
        },
        "L28": {
            "from": "860",
            "to": "836",
            "length": 816.864,
            "phase": "ABCN",
            "cable": "#2  6/1",
            "pole": "IEEE_500"
        },
        "L29": {
            "from": "862",
            "to": "838",
            "length": 1481.328,
            "phase": "BN",
            "cable": "#2  6/1",
            "pole": "IEEE_510"
        }
    },
    "source": {
        "S1": {
            "bus": "800",
            "vrms": 24900.0,
            "frequency": 60.0,
            "phase": "ABC"
        }
    },
    "load": {
        "LD1": {
            "bus": "802",
            "phase": "BC",
            "s": 49244.28900898052,
            "fp": 0.92,
            "ra": 0.0,
            "rb": 7722.170583692476,
            "rc": 7722.170583692476,
            "la": 0.0,
            "lb": 8.726016960414217,
            "lc": 8.726016960414217
        },
        "LD2": {
            "bus": "810",
            "phase": "B",
            "s": 17888.54381999832,
            "fp": 0.92,
            "ra": 0.0,
            "rb": 10628.947884927276,
            "rc": 0.0,
            "la": 0.0,
            "lb": 12.01066183530035,
            "lc": 0.0
        },
        "LD3": {
            "bus": "820",
            "phase": "A",
            "s": 38013.15561749643,
            "fp": 0.92,
            "ra": 5001.857828201071,
            "rb": 0.0,
            "rc": 0.0,
            "la": 5.652076157788401,
            "lb": 0.0,
            "lc": 0.0
        },
        "LD4": {
            "bus": "822",
            "phase": "A",
            "s": 152069.0632574555,
            "fp": 0.92,
            "ra": 1250.3292643954535,
            "rb": 0.0,
            "rc": 0.0,
            "la": 1.412866272373899,
            "lb": 0.0,
            "lc": 0.0
        },
        "LD5": {
            "bus": "824",
            "phase": "B",
            "s": 5385.164807134504,
            "fp": 0.92,
            "ra": 0.0,
            "rb": 35307.44309776721,
            "rc": 0.0,
            "la": 0.0,
            "lb": 39.89724701894076,
            "lc": 0.0
        },
        "LD6": {
            "bus": "826",
            "phase": "B",
            "s": 44721.359549995796,
            "fp": 0.92,
            "ra": 0.0,
            "rb": 4251.57915397091,
            "rc": 0.0,
            "la": 0.0,
            "lb": 4.804264734120141,
            "lc": 0.0
        },
        "LD7": {
            "bus": "828",
            "phase": "C",
            "s": 4472.13595499958,
            "fp": 0.92,
            "ra": 0.0,
            "rb": 0.0,
            "rc": 42515.7915397091,
            "la": 0.0,
            "lb": 0.0,
            "lc": 48.0426473412014
        },
        "LD8": {
            "bus": "830",
            "phase": "ABC",
            "s": 503115.2949374527,
            "fp": 0.92,
            "ra": 1133.7544410589094,
            "rb": 1133.7544410589094,
            "rc": 1133.7544410589094,
            "la": 1.2811372624320376,
            "lb": 1.2811372624320376,
            "lc": 1.2811372624320376
        },
        "LD9": {
            "bus": "830",
            "phase": "A",
            "s": 7615.773105863908,
            "fp": 0.92,
            "ra": 24966.13244078936,
            "rb": 0.0,
            "rc": 0.0,
            "la": 28.21161391776778,
            "lb": 0.0,
            "lc": 0.0
        },
        "LD10": {
            "bus": "856",
            "phase": "B",
            "s": 4472.13595499958,
            "fp": 0.92,
            "ra": 0.0,
            "rb": 42515.791539709106,
            "rc": 0.0,
            "la": 0.0,
            "lb": 48.0426473412014,
            "lc": 0.0
        },
        "LD11": {
            "bus": "858",
            "phase": "ABC",
            "s": 15524.947954824196,
            "fp": 0.92,
            "ra": 36741.4565034179,
            "rb": 36741.4565034179,
            "rc": 36741.4565034179,
            "la": 41.51767551939302,
            "lb": 41.51767551939302,
            "lc": 41.51767551939302
        },
        "LD12": {
            "bus": "864",
            "phase": "A",
            "s": 2236.06797749979,
            "fp": 0.92,
            "ra": 85031.58307941821,
            "rb": 0.0,
            "rc": 0.0,
            "la": 96.0852946824028,
            "lb": 0.0,
            "lc": 0.0
        },
        "LD13": {
            "bus": "834",
            "phase": "ABC",
            "s": 36235.341863986876,
            "fp": 0.92,
            "ra": 15741.791595097693,
            "rb": 15741.791595097693,
            "rc": 15741.791595097693,
            "la": 17.788151525195413,
            "lb": 17.788151525195413,
            "lc": 17.788151525195413
        },
        "LD14": {
            "bus": "844",
            "phase": "ABC",
            "s": 513078.941294612,
            "fp": 0.92,
            "ra": 1111.7376958811271,
            "rb": 1111.7376958811271,
            "rc": 1111.7376958811271,
            "la": 1.2562584424484233,
            "lb": 1.2562584424484233,
            "lc": 1.2562584424484233
        },
        "LD15": {
            "bus": "844",
            "phase": "A",
            "s": 10295.630140987001,
            "fp": 0.92,
            "ra": 18467.679723950576,
            "rb": 0.0,
            "rc": 0.0,
            "la": 20.868392473872866,
            "lb": 0.0,
            "lc": 0.0
        },
        "LD16": {
            "bus": "846",
            "phase": "BC",
            "s": 50537.11507397311,
            "fp": 0.92,
            "ra": 0.0,
            "rb": 7524.6242181291955,
            "rc": 7524.6242181291955,
            "la": 0.0,
            "lb": 8.502790483131571,
            "lc": 8.502790483131571
        },
        "LD17": {
            "bus": "848",
            "phase": "ABC",
            "s": 76837.49084919419,
            "fp": 0.92,
            "ra": 7423.579214989191,
            "rb": 7423.579214989191,
            "rc": 7423.579214989191,
            "la": 8.388610098017212,
            "lb": 8.388610098017212,
            "lc": 8.388610098017212
        },
        "LD18": {
            "bus": "848",
            "phase": "B",
            "s": 25495.097567963923,
            "fp": 0.92,
            "ra": 0.0,
            "rb": 7457.763183417563,
            "rc": 0.0,
            "la": 0.0,
            "lb": 8.427237823868044,
            "lc": 0.0
        },
        "LD19": {
            "bus": "860",
            "phase": "ABC",
            "s": 76837.49084919419,
            "fp": 0.92,
            "ra": 7423.579214989191,
            "rb": 7423.579214989191,
            "rc": 7423.579214989191,
            "la": 8.388610098017212,
            "lb": 8.388610098017212,
            "lc": 8.388610098017212
        },
        "LD20": {
            "bus": "860",
            "phase": "ABC",
            "s": 163232.96235748465,
            "fp": 0.92,
            "ra": 3494.4486197021183,
            "rb": 3494.4486197021183,
            "rc": 3494.4486197021183,
            "la": 3.948710740372719,
            "lb": 3.948710740372719,
            "lc": 3.948710740372719
        },
        "LD21": {
            "bus": "836",
            "phase": "ABC",
            "s": 92590.49627256568,
            "fp": 0.92,
            "ra": 6160.558836630956,
            "rb": 6160.558836630956,
            "rc": 6160.558836630956,
            "la": 6.9614029257000185,
            "lb": 6.9614029257000185,
            "lc": 6.9614029257000185
        },
        "LD22": {
            "bus": "840",
            "phase": "ABC",
            "s": 34205.26275297414,
            "fp": 0.92,
            "ra": 16676.06543821691,
            "rb": 16676.06543821691,
            "rc": 16676.06543821691,
            "la": 18.84387663672635,
            "lb": 18.84387663672635,
            "lc": 18.84387663672635
        },
        "LD23": {
            "bus": "840",
            "phase": "AB",
            "s": 44721.359549995796,
            "fp": 0.92,
            "ra": 8503.15830794182,
            "rb": 8503.15830794182,
            "rc": 0.0,
            "la": 9.608529468240283,
            "lb": 9.608529468240283,
            "lc": 0.0
        },
        "LD24": {
            "bus": "838",
            "phase": "B",
            "s": 31304.951684997057,
            "fp": 0.92,
            "ra": 0.0,
            "rb": 6073.68450567273,
            "rc": 0.0,
            "la": 0.0,
            "lb": 6.863235334457345,
            "lc": 0.0
        }
    },
    "capacitor": {
        "C1": {
            "bus": "844",
            "phase": "ABC",
            "q": 300000.0,
            "ca": 1.283486904178121e-09,
            "cb": 1.283486904178121e-09,
            "cc": 1.283486904178121e-09
        },
        "C2": {
            "bus": "848",
            "phase": "ABC",
            "q": 450000.0,
            "ca": 1.9252303562671816e-09,
            "cb": 1.9252303562671816e-09,
            "cc": 1.9252303562671816e-09
        }
    },
    "surge_arrester": {},
    "pole": {
        "IEEE_500": {
            "phase": "4",
            "distance": 1.0,
            "height": 7.3152,
            "sag": 7.3152
        },
        "IEEE_510": {
            "phase": "2",
            "distance": 0.5,
            "height": 7.3152,
            "sag": 7.3152
        }
    },
    "cable": {
        "#2  6/1": {
            "ri": 0.0,
            "ro": 0.1274064,
            "resistivity": 0.001050119925
        },
        "#4  6/1": {
            "ri": 0.0,
            "ro": 0.1377696,
            "resistivity": 0.001584500478
        },
        "1/0": {
            "ri": 0.0,
            "ro": 0.1359408,
            "resistivity": 0.000695937465
        }
    },
    "surge": {
        "SU1": {
            "bus": "800",
            "amp": 10000.0,
            "tfront": 1.2e-06,
            "tau": 5e-05
        }
    }
}